<system>
	<name>14 And</name>
	<star>
		<name>14 And</name>
		<name>14 Andromedae</name>
		<name>HD 221345</name>
		<name>HIP 116076</name>
		<name>TYC 3231-323-1</name>
		<name>HR 8930</name>
		<name>BD+38 5023</name>
		<name>2MASS J23311742+3914102</name>
		<planet>
			<name>14 And b</name>
			<name>14 Andromedae b</name>
			<name>HD 221345 b</name>
			<list>Confirmed planets</list>
			<semimajoraxis>0.83</semimajoraxis>
			<period errorminus="0.23" errorplus="0.23">185.84</period>
			<periastrontime errorminus="1.5" errorplus="1.5">2452861.4</periastrontime>
			<mass>4.8</mass>
			<discoverymethod>RV</discoverymethod>
			<description>14 Andromedae is an evolved star in the constellation of Andromeda. It was formerly an A-type dwarf.</description>
			<discoveryyear>2008</discoveryyear>
		</planet>
		<mass errorminus="0.2" errorplus="0.1">2.2</mass>
		<radius errorminus="1" errorplus="1">11</radius>
		<temperature errorminus="2" errorplus="2">4813</temperature>
		<metallicity errorminus="0.03" errorplus="0.03">-0.24</metallicity>
		<spectraltype>K0III</spectraltype>
		<magB>6.24</magB>
		<magH errorminus="0.184" errorplus="0.184">2.608</magH>
		<magI>4.1</magI>
		<magJ errorminus="0.18" errorplus="0.18">3.019</magJ>
		<magK errorminus="0.24" errorplus="0.24">2.331</magK>
		<magR>4.6</magR>
		<magV>5.22</magV>
	</star>
	<rightascension>23 31 17.41346</rightascension>
	<declination>+39 14 10.3092</declination>
	<distance errorminus="1.7" errorplus="1.7">79.2</distance>
	<magH errorminus="0.184" errorplus="0.184">2.608</magH>
	<magJ errorminus="0.18" errorplus="0.18">3.019</magJ>
	<magK errorminus="0.24" errorplus="0.24">2.331</magK>
</system>
